[
    {
        "university_name": "Відокремлений структурний підрозділ \"Економіко-технологічний фаховий коледж Херсонського національного технічного університету\"",
        "university_id": "912",
        "university_parent_id": "86",
        "university_short_name": "ВСП \"ЕТФК ХНТУ\"",
        "university_name_en": "Separate structural subdivision \"Professional college of economics and technology of Kherson National Technical University\"",
        "is_from_crimea": "так",
        "registration_year": "1955",
        "university_edrpou": "04606633",
        "university_type_name": "Заклад вищої освіти",
        "university_financing_type_name": "Державна",
        "university_governance_type_name": "Міністерство освіти і науки України",
        "post_index": "29016",
        "katottgcode": "UA68040470010096613",
        "region_name": "Хмельницька область",
        "koatuu_name": "Хмельницький",
        "university_address": "вул. Інститутська, 11",
        "post_index_u": "73008",
        "katottgcodeu": "UA65100150010123057",
        "region_name_u": "Херсонська область",
        "koatuu_name_u": "Херсон",
        "university_address_u": "вул. Бериславське шосе, 22",
        "university_phone": "0552 32-69-22, 32-69-87",
        "university_email": "ett@kntu.net.ua",
        "university_site": "http:\/\/kntu.net.ua\/ukr\/content\/view\/full\/38351",
        "university_director_post": "Директор",
        "university_director_fio": "Шупік Катерина Іванівна",
        "close_date": null,
        "primitki": ""
    },
    {
        "university_name": "Відокремлений структурний підрозділ закладу вищої освіти \"Відкритий міжнародний університет розвитку людини \"Україна\" Хмельницький інститут соціальних технологій",
        "university_id": "236",
        "university_parent_id": "217",
        "university_short_name": "Хмельницький інститут соціальних технологій Університету \"Україна\"",
        "university_name_en": "Separate Structural Subdivision of Higher Education Institution \"Open International University of Human Development \"Ukraine\" Khmelnytskyi Institute of Social Technologies",
        "is_from_crimea": "",
        "registration_year": "1999",
        "university_edrpou": "22779254",
        "university_type_name": "Заклад вищої освіти",
        "university_financing_type_name": "Приватна",
        "university_governance_type_name": "",
        "post_index": "29009",
        "katottgcode": "UA68040470010096613",
        "region_name": "Хмельницька область",
        "koatuu_name": "Хмельницький",
        "university_address": "вул. Ярослава Мудрого, 2А",
        "post_index_u": "29009",
        "katottgcodeu": "UA68040470010096613",
        "region_name_u": "Хмельницька область",
        "koatuu_name_u": "Хмельницький",
        "university_address_u": "вул. Ярослава Мудрого, 2А",
        "university_phone": "(0382) 70-45-56",
        "university_email": "hist_ukraine@ukr.net",
        "university_site": "http:\/\/www.hist.km.ua\/",
        "university_director_post": "Директор",
        "university_director_fio": "Чайковський Михайло Євгенович",
        "close_date": null,
        "primitki": ""
    },
    {
        "university_name": "Відокремлений структурний підрозділ \"Хмельницький торговельно-економічний фаховий коледж Державного торговельно-економічного університету\"",
        "university_id": "6624",
        "university_parent_id": "6594",
        "university_short_name": "ВСП \"ХТЕФК ДТЕУ\"",
        "university_name_en": "Separate Subdivision «Khmelnytsky Professional College of Trade and Economics of State University of Trade and Economics»",
        "is_from_crimea": "",
        "registration_year": "1997",
        "university_edrpou": "01546706",
        "university_type_name": "Заклад вищої освіти",
        "university_financing_type_name": "Державна",
        "university_governance_type_name": "Міністерство освіти і науки України",
        "post_index": "29016",
        "katottgcode": "UA68040470010096613",
        "region_name": "Хмельницька область",
        "koatuu_name": "Хмельницький",
        "university_address": "вул. Кам'янецька, 114",
        "post_index_u": "29016",
        "katottgcodeu": "UA68040470010096613",
        "region_name_u": "Хмельницька область",
        "koatuu_name_u": "Хмельницький",
        "university_address_u": "вул. Кам'янецька, 114",
        "university_phone": "+038(26)-716-04",
        "university_email": "mail@htek.km.ua",
        "university_site": "http:\/\/htek.km.ua",
        "university_director_post": "Директор",
        "university_director_fio": "Гребінська Світлана Іванівна",
        "close_date": null,
        "primitki": ""
    },
    {
        "university_name": "Національна академія Державної прикордонної служби України ім. Богдана Хмельницького",
        "university_id": "94",
        "university_parent_id": null,
        "university_short_name": ".",
        "university_name_en": "National Academy of the State Border Guard Service of Ukraine named after Bohdan Khmelnytskyi",
        "is_from_crimea": "",
        "registration_year": "1992",
        "university_edrpou": "14321481",
        "university_type_name": "Заклад вищої освіти",
        "university_financing_type_name": "Державна",
        "university_governance_type_name": "Адміністрація Державної прикордонної служби України",
        "post_index": "29000",
        "katottgcode": "UA68040470010096613",
        "region_name": "Хмельницька область",
        "koatuu_name": "Хмельницький",
        "university_address": "вул. Шевченка, 46",
        "post_index_u": "29000",
        "katottgcodeu": "UA68040470010096613",
        "region_name_u": "Хмельницька область",
        "koatuu_name_u": "Хмельницький",
        "university_address_u": "вул. Шевченка, 46",
        "university_phone": "(0382) 76-43-68, (0382) 76-30-61",
        "university_email": "nadpsu@dpsu.gov.ua",
        "university_site": "www.nadpsu.edu.ua",
        "university_director_post": "Ректор Національної академії",
        "university_director_fio": "Луцький Олександр Леонтійович",
        "close_date": null,
        "primitki": ""
    },
    {
        "university_name": "Університет економіки і підприємництва",
        "university_id": "156",
        "university_parent_id": null,
        "university_short_name": "УЕП",
        "university_name_en": "University of Economics and Entrepreneurship",
        "is_from_crimea": "",
        "registration_year": "1993",
        "university_edrpou": "22783304",
        "university_type_name": "Заклад вищої освіти",
        "university_financing_type_name": "Приватна",
        "university_governance_type_name": "",
        "post_index": "29016",
        "katottgcode": "UA68040470010096613",
        "region_name": "Хмельницька область",
        "koatuu_name": "Хмельницький",
        "university_address": "Львівське шосе , 51\/2",
        "post_index_u": "29016",
        "katottgcodeu": "UA68040470010096613",
        "region_name_u": "Хмельницька область",
        "koatuu_name_u": "Хмельницький",
        "university_address_u": "Львівське шосе , 51\/2",
        "university_phone": "0382 72 82 50, 72 53 87",
        "university_email": "hiep@infokom.uf",
        "university_site": "http:\/ www.uniep.km.uа",
        "university_director_post": "Ректор",
        "university_director_fio": "Желавський Олег Борисович",
        "close_date": null,
        "primitki": ""
    },
    {
        "university_name": "Херсонський національний технічний університет",
        "university_id": "86",
        "university_parent_id": null,
        "university_short_name": "ХНТУ",
        "university_name_en": "Kherson national technical university",
        "is_from_crimea": "так",
        "registration_year": "1959",
        "university_edrpou": "05480298",
        "university_type_name": "Заклад вищої освіти",
        "university_financing_type_name": "Державна",
        "university_governance_type_name": "Міністерство освіти і науки України",
        "post_index": "29016",
        "katottgcode": "UA68040470010096613",
        "region_name": "Хмельницька область",
        "koatuu_name": "Хмельницький",
        "university_address": "вул. Інститутська, 11",
        "post_index_u": "73000",
        "katottgcodeu": "UA65100150010123057",
        "region_name_u": "Херсонська область",
        "koatuu_name_u": "Херсон",
        "university_address_u": "Бериславське шосе , 24",
        "university_phone": "+38 (0382) 77-35-65, +38 (0552) 32-69-09, 32-69-10",
        "university_email": "kntu@kntu.net.uа",
        "university_site": "http:\/\/www.kntu.net.ua",
        "university_director_post": "В.о. ректор",
        "university_director_fio": "Чепелюк Олена Валеріївна",
        "close_date": null,
        "primitki": ""
    },
    {
        "university_name": "Хмельницька гуманітарно-педагогічна академія",
        "university_id": "112",
        "university_parent_id": null,
        "university_short_name": "ХГПА",
        "university_name_en": "Khmelnytskyi Humanitarian-Pedagogical Academy",
        "is_from_crimea": "",
        "registration_year": "1921",
        "university_edrpou": "02138872",
        "university_type_name": "Заклад вищої освіти",
        "university_financing_type_name": "Комунальна",
        "university_governance_type_name": "Обласна рада",
        "post_index": "29013",
        "katottgcode": "UA68040470010096613",
        "region_name": "Хмельницька область",
        "koatuu_name": "Хмельницький",
        "university_address": "вул. Проскурівського підпілля, 139",
        "post_index_u": "29013",
        "katottgcodeu": "UA68040470010096613",
        "region_name_u": "Хмельницька область",
        "koatuu_name_u": "Хмельницький",
        "university_address_u": "вул. Проскурівського підпілля, 139",
        "university_phone": "(0382) 79 53 55, 79 59 45, 79 51 68",
        "university_email": "kgpa@ukr.net",
        "university_site": "http:\/\/www.kgpa.km.ua",
        "university_director_post": "Ректор",
        "university_director_fio": "Шоробура Інна Михайлівна",
        "close_date": null,
        "primitki": ""
    },
    {
        "university_name": "Хмельницький інститут імені Блаженнішого Володимира, Митрополита Київського і всієї України Приватного акціонерного товариства \"Вищий навчальний заклад \"Міжрегіональна Академія управління персоналом\"",
        "university_id": "1198",
        "university_parent_id": "249",
        "university_short_name": "ХІ ПрАТ «ВНЗ «МАУП»",
        "university_name_en": "The Khmelnytskyi His Beatitude Metropolitan Volodymyr of Kyiv and All Ukraine Institute of the Private Joint Stock Company \"Higher education institution \"The Interregional Academy of Personnel Management\"",
        "is_from_crimea": "",
        "registration_year": "2000",
        "university_edrpou": "22780406",
        "university_type_name": "Заклад вищої освіти",
        "university_financing_type_name": "Приватна",
        "university_governance_type_name": "",
        "post_index": "29015",
        "katottgcode": "UA68040470010096613",
        "region_name": "Хмельницька область",
        "koatuu_name": "Хмельницький",
        "university_address": "просп. Миру, 101-А",
        "post_index_u": "29015",
        "katottgcodeu": "UA68040470010096613",
        "region_name_u": "Хмельницька область",
        "koatuu_name_u": "Хмельницький",
        "university_address_u": "просп. Миру, 101-А",
        "university_phone": "(0382) 71 66 15",
        "university_email": "himaup@ukr.net",
        "university_site": "maup.km.ua",
        "university_director_post": "Директор",
        "university_director_fio": "Білий Леонід Григорович",
        "close_date": null,
        "primitki": ""
    },
    {
        "university_name": "Хмельницький кооперативний торговельно-економічний інститут",
        "university_id": "254",
        "university_parent_id": null,
        "university_short_name": "ХКТЕІ",
        "university_name_en": "Khmelnytskyi Cooperative Trade and Economic Institute",
        "is_from_crimea": "",
        "registration_year": "1957",
        "university_edrpou": "35805541",
        "university_type_name": "Заклад вищої освіти",
        "university_financing_type_name": "Приватна",
        "university_governance_type_name": "Укоопспілка",
        "post_index": "29000",
        "katottgcode": "UA68040470010096613",
        "region_name": "Хмельницька область",
        "koatuu_name": "Хмельницький",
        "university_address": "вул. Кам’янецька, 3",
        "post_index_u": "29000",
        "katottgcodeu": "UA68040470010096613",
        "region_name_u": "Хмельницька область",
        "koatuu_name_u": "Хмельницький",
        "university_address_u": "вул. Кам’янецька, 3",
        "university_phone": "0382-79-55-68",
        "university_email": "xktei@ukr.net",
        "university_site": "www.xktei.km.ua",
        "university_director_post": "В.о. ректора",
        "university_director_fio": "Телячий Юрій Васильович",
        "close_date": null,
        "primitki": ""
    },
    {
        "university_name": "Хмельницький національний університет",
        "university_id": "138",
        "university_parent_id": null,
        "university_short_name": "ХНУ",
        "university_name_en": "Khmelnytskyi National University",
        "is_from_crimea": "так",
        "registration_year": "1962",
        "university_edrpou": "02071234",
        "university_type_name": "Заклад вищої освіти",
        "university_financing_type_name": "Державна",
        "university_governance_type_name": "Міністерство освіти і науки України",
        "post_index": "29016",
        "katottgcode": "UA68040470010096613",
        "region_name": "Хмельницька область",
        "koatuu_name": "Хмельницький",
        "university_address": "вул. Інститутська, 11",
        "post_index_u": "29016",
        "katottgcodeu": "UA68040470010096613",
        "region_name_u": "Хмельницька область",
        "koatuu_name_u": "Хмельницький",
        "university_address_u": "вул. Інститутська, 11",
        "university_phone": "+380(38)-267-27-55",
        "university_email": "centr@khnu.km.ua",
        "university_site": "http:\/\/www.khnu.km.ua",
        "university_director_post": "Ректор",
        "university_director_fio": "Матюх Сергій Анатолійович",
        "close_date": null,
        "primitki": ""
    },
    {
        "university_name": "Хмельницький університет управління та права імені Леоніда Юзькова",
        "university_id": "275",
        "university_parent_id": null,
        "university_short_name": "ХУУП імені Леоніда Юзькова",
        "university_name_en": "leonid Yuzkov Khmelnytskyi University of Management and Law",
        "is_from_crimea": "",
        "registration_year": "1995",
        "university_edrpou": "14163438",
        "university_type_name": "Заклад вищої освіти",
        "university_financing_type_name": "Комунальна",
        "university_governance_type_name": "Обласна рада",
        "post_index": "29000",
        "katottgcode": "UA68040470010096613",
        "region_name": "Хмельницька область",
        "koatuu_name": "Хмельницький",
        "university_address": "вул. Героїв Майдану, 8",
        "post_index_u": "29000",
        "katottgcodeu": "UA68040470010096613",
        "region_name_u": "Хмельницька область",
        "koatuu_name_u": "Хмельницький",
        "university_address_u": "вул. Героїв Майдану, 8",
        "university_phone": "(0382) 71-80-00; 71-75-70",
        "university_email": "info@univer.km.ua",
        "university_site": "www.univer.km.ua",
        "university_director_post": "Ректор",
        "university_director_fio": "Омельчук Олег Миколайович",
        "close_date": null,
        "primitki": ""
    },
    {
        "university_name": "Хмельницький фаховий економіко-технологічний коледж Університету економіки і підприємництва",
        "university_id": "1457",
        "university_parent_id": "156",
        "university_short_name": "ХФЕТК УЕП",
        "university_name_en": "Khmelnytskyi Professional College of Economic and Technology of University of Economics and Entrepreneurship",
        "is_from_crimea": "",
        "registration_year": "2012",
        "university_edrpou": "38171258",
        "university_type_name": "Заклад вищої освіти",
        "university_financing_type_name": "Приватна",
        "university_governance_type_name": "",
        "post_index": "29016",
        "katottgcode": "UA68040470010096613",
        "region_name": "Хмельницька область",
        "koatuu_name": "Хмельницький",
        "university_address": "вул. Молодіжна, 12\/1",
        "post_index_u": "29000",
        "katottgcodeu": "UA68040470010096613",
        "region_name_u": "Хмельницька область",
        "koatuu_name_u": "Хмельницький",
        "university_address_u": "Львівське шосе , 51\/2",
        "university_phone": "0382 72 82 50",
        "university_email": "uniepkm@gmail.com",
        "university_site": "uniepkm.km.ua",
        "university_director_post": "В.о. ректора",
        "university_director_fio": "Желавський Олег Борисович",
        "close_date": null,
        "primitki": ""
    },
    {
        "university_name": "Відокремлений структурний підрозділ «Кам’янець-Подільський фаховий коледж Закладу вищої освіти «Подільський державний університет»",
        "university_id": "1079",
        "university_parent_id": "177",
        "university_short_name": "ВСП «КПФК ЗВО «ПДУ»",
        "university_name_en": "Affiliated Unit \"Kamianets-Podilskyi Vocational College of Higher Educational Institution \"Podillia State University\"",
        "is_from_crimea": "",
        "registration_year": "2004",
        "university_edrpou": "00729020",
        "university_type_name": "Заклад вищої освіти",
        "university_financing_type_name": "Державна",
        "university_governance_type_name": "Міністерство освіти і науки України",
        "post_index": "32300",
        "katottgcode": "UA68020110010097898",
        "region_name": "Хмельницька область",
        "koatuu_name": "Кам'янець-Подільський",
        "university_address": "вул. Лесі Українки, 95",
        "post_index_u": "32300",
        "katottgcodeu": "UA68020110010097898",
        "region_name_u": "Хмельницька область",
        "koatuu_name_u": "Кам'янець-Подільський",
        "university_address_u": "вул. Лесі Українки, 95",
        "university_phone": "(03849) 2 11 21",
        "university_email": "koledg_pdatu@ukr.net",
        "university_site": "koledg-pdatu.km.ua",
        "university_director_post": "Директор",
        "university_director_fio": "Білянський Юрій Олександрович",
        "close_date": null,
        "primitki": ""
    },
    {
        "university_name": "Заклад вищої освіти «Подільський державний університет»",
        "university_id": "177",
        "university_parent_id": null,
        "university_short_name": "ЗВО \"ПДУ\"",
        "university_name_en": "Higher educational institution «Рodillia State University»",
        "is_from_crimea": "так",
        "registration_year": "1919",
        "university_edrpou": "22769675",
        "university_type_name": "Заклад вищої освіти",
        "university_financing_type_name": "Державна",
        "university_governance_type_name": "Міністерство освіти і науки України",
        "post_index": "32316",
        "katottgcode": "UA68020110010097898",
        "region_name": "Хмельницька область",
        "koatuu_name": "Кам'янець-Подільський",
        "university_address": "вул. Шевченка, 12",
        "post_index_u": "32316",
        "katottgcodeu": "UA68020110010097898",
        "region_name_u": "Хмельницька область",
        "koatuu_name_u": "Кам'янець-Подільський",
        "university_address_u": "вул. Шевченка, 12",
        "university_phone": "038 497 62 85",
        "university_email": "main@pdatu.edu.ua",
        "university_site": "http:\/\/www.pdatu.edu.ua",
        "university_director_post": "Ректор",
        "university_director_fio": "Іванишин Володимир Васильович",
        "close_date": null,
        "primitki": ""
    },
    {
        "university_name": "Кам'янець-Подільська філія Національного університету харчових технологій",
        "university_id": "978",
        "university_parent_id": "47",
        "university_short_name": "К-ПФНУХТ",
        "university_name_en": "Kamianetz-Podilsk Branch of the National University of Food Technologies",
        "is_from_crimea": "",
        "registration_year": "2008",
        "university_edrpou": "25993982",
        "university_type_name": "Заклад вищої освіти",
        "university_financing_type_name": "Державна",
        "university_governance_type_name": "Міністерство освіти і науки України",
        "post_index": "32300",
        "katottgcode": "UA68020110010097898",
        "region_name": "Хмельницька область",
        "koatuu_name": "Кам'янець-Подільський",
        "university_address": "вул. Суворова, 2",
        "post_index_u": "01601",
        "katottgcodeu": "UA80000000000093317",
        "region_name_u": "КИЇВ",
        "koatuu_name_u": "Київ",
        "university_address_u": "вул. Володимирська, 68",
        "university_phone": "03849 9 11 60",
        "university_email": "dekankp@ukr.net",
        "university_site": "usuft.kp.km.ua",
        "university_director_post": "В.о. директора",
        "university_director_fio": "Банзула Каріна Євгенівна",
        "close_date": null,
        "primitki": ""
    },
    {
        "university_name": "Кам'янець-Подільський національний університет імені Івана Огієнка",
        "university_id": "178",
        "university_parent_id": null,
        "university_short_name": "К-ПНУ",
        "university_name_en": "Kamianets-Podilskyi Ivan Ohiienko National University",
        "is_from_crimea": "так",
        "registration_year": "1918",
        "university_edrpou": "02125616",
        "university_type_name": "Заклад вищої освіти",
        "university_financing_type_name": "Державна",
        "university_governance_type_name": "Міністерство освіти і науки України",
        "post_index": "32300",
        "katottgcode": "UA68020110010097898",
        "region_name": "Хмельницька область",
        "koatuu_name": "Кам'янець-Подільський",
        "university_address": "вул. Огієнка, 61",
        "post_index_u": "32300",
        "katottgcodeu": "UA68020110010097898",
        "region_name_u": "Хмельницька область",
        "koatuu_name_u": "Кам'янець-Подільський",
        "university_address_u": "вул. Огієнка, 61",
        "university_phone": "(03849)3-05-13, (03849)3-16-31 (03849)3-07-83ф",
        "university_email": "post@kpnu.edu.ua",
        "university_site": "www.kpnu.edu.ua",
        "university_director_post": "Ректор",
        "university_director_fio": "Копилов Сергій Анатолійович",
        "close_date": null,
        "primitki": ""
    },
    {
        "university_name": "Навчально-реабілітаційний заклад вищої освіти \"Кам'янець-Подільський державний інститут\"",
        "university_id": "6512",
        "university_parent_id": null,
        "university_short_name": "НРЗВО КПДІ",
        "university_name_en": "Educational and Rehabilitation Institution of Higher Education \"Kamianets-Podilskyi State Institute\"",
        "is_from_crimea": "так",
        "registration_year": "2021",
        "university_edrpou": "44370030",
        "university_type_name": "Заклад вищої освіти",
        "university_financing_type_name": "Державна",
        "university_governance_type_name": "Міністерство освіти і науки України",
        "post_index": "32300",
        "katottgcode": "UA68020110010097898",
        "region_name": "Хмельницька область",
        "koatuu_name": "Кам'янець-Подільський",
        "university_address": "вул. Годованця, 13",
        "post_index_u": "32300",
        "katottgcodeu": "UA68020110010097898",
        "region_name_u": "Хмельницька область",
        "koatuu_name_u": "Кам'янець-Подільський",
        "university_address_u": "вул. Годованця, 13",
        "university_phone": "(038)432-66-23",
        "university_email": "info@kpdi.edu.ua",
        "university_site": "https:\/\/kpdi.edu.ua\/",
        "university_director_post": "Виконуючий обов'язки ректора",
        "university_director_fio": "Тріпак Мар`ян Миколайович",
        "close_date": null,
        "primitki": ""
    },
    {
        "university_name": "Приватний заклад вищої освіти \"Кам`янець-Подільський податковий інститут\"",
        "university_id": "4083",
        "university_parent_id": null,
        "university_short_name": "ПЗВО К-ППІ",
        "university_name_en": "Private institution of higher education «Kamyanets-Podilsky tax institute»",
        "is_from_crimea": "",
        "registration_year": "2017",
        "university_edrpou": "41757627",
        "university_type_name": "Заклад вищої освіти",
        "university_financing_type_name": "Приватна",
        "university_governance_type_name": "",
        "post_index": "32300",
        "katottgcode": "UA68020110010097898",
        "region_name": "Хмельницька область",
        "koatuu_name": "Кам'янець-Подільський",
        "university_address": "вул. Годованця, 1",
        "post_index_u": "32300",
        "katottgcodeu": "UA68020110010097898",
        "region_name_u": "Хмельницька область",
        "koatuu_name_u": "Кам'янець-Подільський",
        "university_address_u": "вул. Годованця, 1",
        "university_phone": "+038(49)-909-88",
        "university_email": "podinstitutk_p@ukr.net",
        "university_site": "",
        "university_director_post": "Ректор",
        "university_director_fio": "Савчук Денис Анатолійович",
        "close_date": null,
        "primitki": ""
    },
    {
        "university_name": "Фаховий коледж економіки, права та інформаційних технологій",
        "university_id": "4308",
        "university_parent_id": "4083",
        "university_short_name": "ФКЕПІТ К-ППІ",
        "university_name_en": "Professional College of Economics, Law and Information Technologies of Kamyanets-Podilsky Tax Institute",
        "is_from_crimea": "",
        "registration_year": "2018",
        "university_edrpou": "42833221",
        "university_type_name": "Заклад вищої освіти",
        "university_financing_type_name": "Приватна",
        "university_governance_type_name": "",
        "post_index": "32300",
        "katottgcode": "UA68020110010097898",
        "region_name": "Хмельницька область",
        "koatuu_name": "Кам'янець-Подільський",
        "university_address": "вул. Годованця, 1",
        "post_index_u": "32300",
        "katottgcodeu": "UA68020110010097898",
        "region_name_u": "Хмельницька область",
        "koatuu_name_u": "Кам'янець-Подільський",
        "university_address_u": "вул. Годованця, 1",
        "university_phone": "(03849) 7-44-54",
        "university_email": "podatkovyikp@gmail.com, podatkovyi@gmail.com",
        "university_site": "podatkovyi.com",
        "university_director_post": "Директор",
        "university_director_fio": "Савчук Вікторія Юріївна",
        "close_date": null,
        "primitki": ""
    },
    {
        "university_name": "Відокремлений структурний підрозділ \" Шепетівський фаховий коледж Закладу вищої освіти \"Подільський державний університет\"",
        "university_id": "963",
        "university_parent_id": "177",
        "university_short_name": "ВСП ШФК ЗВО \"ПДУ\"",
        "university_name_en": "Affiated Unit \"Shepetivka Vocational College of Higher Educational Institution \"Podillia State University\"",
        "is_from_crimea": "",
        "registration_year": "2005",
        "university_edrpou": "34363226",
        "university_type_name": "Заклад вищої освіти",
        "university_financing_type_name": "Державна",
        "university_governance_type_name": "Міністерство освіти і науки України",
        "post_index": "30400",
        "katottgcode": "UA68060330010023704",
        "region_name": "Хмельницька область",
        "koatuu_name": "Шепетівка",
        "university_address": "просп. Миру, 25",
        "post_index_u": "30400",
        "katottgcodeu": "UA68060330010023704",
        "region_name_u": "Хмельницька область",
        "koatuu_name_u": "Шепетівка",
        "university_address_u": "просп. Миру, 25",
        "university_phone": "+038(40) 4- 07-63",
        "university_email": "shepkol@ukr.net",
        "university_site": "shepteh.km.ua",
        "university_director_post": "Директор",
        "university_director_fio": "Дмитрик Валентина Володимирівна",
        "close_date": null,
        "primitki": ""
    },
    {
        "university_name": "Відокремлений структурний підрозділ \"Новоушицький фаховий коледж Закладу вищої освіти \"Подільський державний університет\"",
        "university_id": "958",
        "university_parent_id": "177",
        "university_short_name": "ВСП \"НФК ЗВО \"ПДУ\"",
        "university_name_en": "Affiliated Unit “Nova Ushytsia Vocational College of Higher Educational Institution “Podillia State University”",
        "is_from_crimea": "",
        "registration_year": "1930",
        "university_edrpou": "34114840",
        "university_type_name": "Заклад вищої освіти",
        "university_financing_type_name": "Державна",
        "university_governance_type_name": "Міністерство освіти і науки України",
        "post_index": "32600",
        "katottgcode": "UA68020190010042454",
        "region_name": "Хмельницька область",
        "koatuu_name": "Нова Ушиця",
        "university_address": "вул. Подільська, 34",
        "post_index_u": "32600",
        "katottgcodeu": "UA68020190010042454",
        "region_name_u": "Хмельницька область",
        "koatuu_name_u": "Нова Ушиця",
        "university_address_u": "вул. Подільська, 34",
        "university_phone": "0384 73 00 67",
        "university_email": "nfk-pdatu@ukr.net",
        "university_site": "ntpu.org.ua",
        "university_director_post": "Директор",
        "university_director_fio": "Івасик Мирослава Володимирівна",
        "close_date": null,
        "primitki": ""
    }
]